ng_slice_download/__init__.py
ng_slice_download/cli.py
ng_slice_download/cuboid.py
ng_slice_download/plane.py
ng_slice_download/utils.py
ng_slice_download-0.2.dist-info/WHEEL
ng_slice_download-0.2.dist-info/entry_points.txt
ng_slice_download-0.2.dist-info/METADATA
ng_slice_download-0.2.dist-info/RECORD
