Metadata-Version: 2.3
Name: ng-slice-download
Version: 0.2
Summary: Download slices from a neuroglancer view
Requires-Dist: click>=8.3.1
Requires-Dist: inquirer>=3.4.1
Requires-Dist: neuroglancer>=2.41.2
Requires-Dist: numpy>=2.4.1
Requires-Dist: scipy>=1.17.0
Requires-Dist: tensorstore>=0.1.80
Requires-Dist: tifffile>=2026.1.14
Requires-Dist: tqdm>=4.67.1
Requires-Python: >=3.12
